pyavo/__init__.py
pyavo/_version.py
pyavo/pyavo.py
pyavo/requirements.txt
pyavo/avotools/__init__.py
pyavo/avotools/approx.py
pyavo/avotools/gassmann.py
pyavo/avotools/impedance.py
pyavo/avotools/log_crossplot.py
pyavo/avotools/moduli.py
pyavo/seismodel/__init__.py
pyavo/seismodel/angle_stack.py
pyavo/seismodel/rpm.py
pyavo/seismodel/tuning_prestack.py
pyavo/seismodel/tuning_wedge.py
pyavo/seismodel/wavelet.py
pyavo-0.1.4.dist-info/LICENSE
pyavo-0.1.4.dist-info/METADATA
pyavo-0.1.4.dist-info/WHEEL
pyavo-0.1.4.dist-info/top_level.txt
pyavo-0.1.4.dist-info/RECORD
