Metadata-Version: 2.1
Name: pyavo
Version: 0.1.4
Summary: AVO Analysis in Python
Home-page: https://github.com/TolaAbiodun/pyavo
Author: Tola Abiodun
Author-email: tola.abiodun@fluxgateng.com
License: MIT
Platform: UNKNOWN
Classifier: Programming Language :: Python :: 3.6
Classifier: Programming Language :: Python :: 3.7
Classifier: License :: OSI Approved :: MIT License
Classifier: Operating System :: OS Independent
Requires-Python: >=3.6
Requires-Dist: matplotlib
Requires-Dist: pandas
Requires-Dist: numpy
Requires-Dist: las
Requires-Dist: xarray
Requires-Dist: segyio
Requires-Dist: bruges
